user_context_remote/__init__.py
user_context_remote/user_context.py
user_context_remote-0.0.121.dist-info/METADATA
user_context_remote-0.0.121.dist-info/WHEEL
user_context_remote-0.0.121.dist-info/top_level.txt
user_context_remote-0.0.121.dist-info/RECORD
