Metadata-Version: 2.4
Name: user-context-remote
Version: 0.0.121
Summary: PyPI Package for Circles User Context Local/Remote Python
Home-page: https://github.com/circles-zone/user-context-remote-python-package
Author: Circles
Author-email: info@circlez.ai
Classifier: Programming Language :: Python :: 3
Classifier: Operating System :: OS Independent
Requires-Dist: language-remote>=0.0.15
Requires-Dist: url-remote>=0.0.15
Requires-Dist: requests>=2.31.0
Requires-Dist: python-sdk-remote>=0.0.44
Dynamic: author
Dynamic: author-email
Dynamic: classifier
Dynamic: description
Dynamic: description-content-type
Dynamic: home-page
Dynamic: requires-dist
Dynamic: summary
